asyncai/AsyncAI.py
asyncai/__init__.py
AsyncAI-0.0.1.dist-info/METADATA
AsyncAI-0.0.1.dist-info/WHEEL
AsyncAI-0.0.1.dist-info/top_level.txt
AsyncAI-0.0.1.dist-info/RECORD
