Metadata-Version: 2.1
Name: AsyncAI
Version: 0.0.1
Summary: Enter AsyncAI models with API
Author: AsyncAI
Author-email: <asyncintellect@gmail.com>
Keywords: python,api,ai,datascience
Classifier: Development Status :: 1 - Planning
Classifier: Intended Audience :: Developers
Classifier: Programming Language :: Python :: 3
Classifier: Operating System :: Unix
Classifier: Operating System :: MacOS :: MacOS X
Classifier: Operating System :: Microsoft :: Windows
